EPyQt/__init__.py
EPyQt/EWidgets/__init__.py
EPyQt-0.0.0.dist-info/LICENSE
EPyQt-0.0.0.dist-info/METADATA
EPyQt-0.0.0.dist-info/WHEEL
EPyQt-0.0.0.dist-info/top_level.txt
EPyQt-0.0.0.dist-info/RECORD
