Metadata-Version: 2.1
Name: EPyQt
Version: 0.0.0
Summary: A elegant and pretty lib of PyQt Widgets
Home-page: http://lyt0628.icu
Download-URL: http://github.com//LYT0628/element-pyqt
Author: lyt0628
Author-email: lyt0628 <lyt.0628@qq.com>
License: BSD 2-Clause License
Project-URL: Repository, https://github.com/LYT0628/epyqt
Project-URL: Documentation, http://lyt0628.icu/docs/epyqt
Project-URL: Issues, https://github.com/LYT0628/epyqt/issues
Project-URL: Official Website, https://lyt0628.icu
Keywords: pyqt,gui
Classifier: Development Status :: 1 - Planning
Classifier: Programming Language :: Python :: 3
Classifier: License :: OSI Approved :: BSD License
Classifier: Operating System :: OS Independent
Classifier: Natural Language :: Chinese (Simplified)
Classifier: Topic :: Utilities
Requires-Python: >=3.8
License-File: LICENSE
Requires-Dist: PyQt6
